<?xml version="1.0"?>
<Level xmlns:xsi="http://www.w3.org/2001/XMLSchema-instance" xmlns:xsd="http://www.w3.org/2001/XMLSchema">
  <LevelType>Normal</LevelType>
  <BgPalette>2</BgPalette>
  <TilesetId>0</TilesetId>
  <Tiles>
    <ArrayOfString>
      <string>0-0-4-3</string>
      <string>0-0-0-2</string>
      <string>0-0-2-3</string>
      <string>0-0-2-2</string>
      <string>0-0-0-3</string>
      <string>0-1-0-2</string>
      <string>0-1-0-2</string>
      <string>0-1-0-2</string>
      <string>0-1-0-2</string>
      <string>0-1-0-2</string>
      <string>0-1-0-2</string>
      <string>0-1-0-2</string>
      <string>2-0-3-4</string>
      <string>2-0-3-5</string>
      <string>2-0-4-3</string>
    </ArrayOfString>
    <ArrayOfString>
      <string>0-0-4-3</string>
      <string>0-0-1-2</string>
      <string>0-0-3-3</string>
      <string>0-0-0-1</string>
      <string>0-0-3-1</string>
      <string>0-1-0-2</string>
      <string>0-1-0-2</string>
      <string>0-1-0-2</string>
      <string>0-1-0-2</string>
      <string>1-1-5-0</string>
      <string>0-1-0-2</string>
      <string>0-1-0-2</string>
      <string>2-0-3-4</string>
      <string>2-0-3-5</string>
      <string>2-0-4-3</string>
    </ArrayOfString>
    <ArrayOfString>
      <string>0-0-4-3</string>
      <string>0-0-4-0</string>
      <string>0-0-4-1</string>
      <string>0-0-2-0</string>
      <string>0-0-2-1</string>
      <string>0-1-0-2</string>
      <string>0-1-0-2</string>
      <string>0-1-0-2</string>
      <string>0-1-0-2</string>
      <string>0-1-0-2</string>
      <string>0-1-0-2</string>
      <string>0-1-0-2</string>
      <string>2-0-3-4</string>
      <string>2-0-3-5</string>
      <string>2-0-4-3</string>
    </ArrayOfString>
    <ArrayOfString>
      <string>0-0-4-3</string>
      <string>0-0-5-0</string>
      <string>0-0-5-1</string>
      <string>0-0-3-0</string>
      <string>0-0-3-1</string>
      <string>0-1-0-2</string>
      <string>0-1-0-2</string>
      <string>0-1-0-2</string>
      <string>0-1-0-2</string>
      <string>1-1-5-0</string>
      <string>0-1-0-2</string>
      <string>0-1-0-2</string>
      <string>2-0-3-4</string>
      <string>2-0-3-5</string>
      <string>2-0-4-3</string>
    </ArrayOfString>
    <ArrayOfString>
      <string>0-0-4-3</string>
      <string>0-0-4-0</string>
      <string>0-0-4-1</string>
      <string>0-0-2-0</string>
      <string>0-0-2-1</string>
      <string>0-1-0-2</string>
      <string>0-1-0-2</string>
      <string>0-1-0-2</string>
      <string>0-1-0-2</string>
      <string>0-1-0-2</string>
      <string>0-1-0-2</string>
      <string>0-1-0-2</string>
      <string>2-0-3-4</string>
      <string>2-0-3-5</string>
      <string>2-0-4-3</string>
    </ArrayOfString>
    <ArrayOfString>
      <string>0-0-4-3</string>
      <string>0-0-5-0</string>
      <string>0-0-5-1</string>
      <string>0-0-3-0</string>
      <string>0-0-3-1</string>
      <string>0-1-0-2</string>
      <string>0-1-0-2</string>
      <string>0-1-0-2</string>
      <string>0-1-0-2</string>
      <string>0-1-0-2</string>
      <string>2-0-4-2</string>
      <string>2-0-4-2</string>
      <string>2-0-3-4</string>
      <string>2-0-3-5</string>
      <string>2-0-4-3</string>
    </ArrayOfString>
    <ArrayOfString>
      <string>0-0-4-3</string>
      <string>0-0-4-0</string>
      <string>0-0-4-1</string>
      <string>0-0-2-0</string>
      <string>0-0-2-1</string>
      <string>1-1-2-0</string>
      <string>1-1-2-1</string>
      <string>1-1-2-1</string>
      <string>1-1-2-1</string>
      <string>1-1-2-1</string>
      <string>2-0-4-2</string>
      <string>2-0-4-2</string>
      <string>2-0-3-4</string>
      <string>2-0-3-5</string>
      <string>2-0-4-3</string>
    </ArrayOfString>
    <ArrayOfString>
      <string>0-0-4-3</string>
      <string>0-0-5-0</string>
      <string>0-0-5-1</string>
      <string>0-0-3-0</string>
      <string>0-0-3-1</string>
      <string>0-1-0-2</string>
      <string>0-1-0-2</string>
      <string>0-1-0-2</string>
      <string>0-1-0-2</string>
      <string>0-1-0-2</string>
      <string>0-1-0-2</string>
      <string>0-1-0-2</string>
      <string>2-0-3-4</string>
      <string>2-0-3-5</string>
      <string>2-0-4-3</string>
    </ArrayOfString>
    <ArrayOfString>
      <string>0-0-4-3</string>
      <string>0-0-4-0</string>
      <string>0-0-4-1</string>
      <string>0-0-2-0</string>
      <string>0-0-2-1</string>
      <string>0-1-0-2</string>
      <string>0-1-0-2</string>
      <string>0-1-0-2</string>
      <string>0-1-0-2</string>
      <string>0-1-0-2</string>
      <string>0-1-0-2</string>
      <string>0-1-0-2</string>
      <string>0-1-0-2</string>
      <string>3-1-0-7</string>
      <string>3-1-0-7</string>
    </ArrayOfString>
    <ArrayOfString>
      <string>0-0-4-3</string>
      <string>0-0-5-0</string>
      <string>0-0-5-1</string>
      <string>0-0-3-0</string>
      <string>0-0-3-1</string>
      <string>0-1-0-2</string>
      <string>0-1-0-2</string>
      <string>0-1-0-2</string>
      <string>0-1-0-2</string>
      <string>0-1-0-2</string>
      <string>0-1-0-2</string>
      <string>0-1-0-2</string>
      <string>0-1-0-2</string>
      <string>3-1-0-7</string>
      <string>3-1-0-7</string>
    </ArrayOfString>
    <ArrayOfString>
      <string>0-0-4-3</string>
      <string>0-0-4-0</string>
      <string>0-0-4-1</string>
      <string>0-0-2-0</string>
      <string>0-0-2-1</string>
      <string>0-1-0-2</string>
      <string>0-1-0-2</string>
      <string>2-2-2-1</string>
      <string>2-0-3-4</string>
      <string>2-0-3-5</string>
      <string>0-1-0-2</string>
      <string>0-1-0-2</string>
      <string>2-0-3-4</string>
      <string>2-0-3-5</string>
      <string>2-0-4-3</string>
    </ArrayOfString>
    <ArrayOfString>
      <string>0-0-4-3</string>
      <string>0-0-5-0</string>
      <string>0-0-5-1</string>
      <string>0-0-3-0</string>
      <string>0-0-3-1</string>
      <string>0-1-0-2</string>
      <string>0-1-0-2</string>
      <string>2-2-2-1</string>
      <string>2-0-3-4</string>
      <string>2-0-3-5</string>
      <string>1-1-2-0</string>
      <string>1-1-2-1</string>
      <string>2-0-3-4</string>
      <string>2-0-3-5</string>
      <string>2-0-4-3</string>
    </ArrayOfString>
    <ArrayOfString>
      <string>0-0-4-3</string>
      <string>0-0-4-0</string>
      <string>0-0-4-1</string>
      <string>0-0-2-0</string>
      <string>0-0-2-1</string>
      <string>0-1-0-2</string>
      <string>0-1-0-2</string>
      <string>2-2-2-1</string>
      <string>2-0-3-4</string>
      <string>2-0-3-5</string>
      <string>0-1-0-2</string>
      <string>0-1-0-2</string>
      <string>2-0-3-4</string>
      <string>2-0-3-5</string>
      <string>2-0-4-3</string>
    </ArrayOfString>
    <ArrayOfString>
      <string>0-0-4-3</string>
      <string>0-0-5-0</string>
      <string>0-0-5-1</string>
      <string>0-0-3-0</string>
      <string>0-0-3-1</string>
      <string>0-1-0-2</string>
      <string>0-1-0-2</string>
      <string>2-2-2-1</string>
      <string>2-0-3-4</string>
      <string>2-0-3-5</string>
      <string>0-1-0-2</string>
      <string>0-1-0-2</string>
      <string>2-0-3-4</string>
      <string>2-0-3-5</string>
      <string>2-0-4-3</string>
    </ArrayOfString>
    <ArrayOfString>
      <string>0-0-4-3</string>
      <string>0-0-4-0</string>
      <string>0-0-4-1</string>
      <string>0-0-2-0</string>
      <string>0-0-2-1</string>
      <string>0-1-0-2</string>
      <string>0-1-0-2</string>
      <string>2-2-2-1</string>
      <string>2-0-3-4</string>
      <string>2-0-3-5</string>
      <string>0-1-0-2</string>
      <string>0-1-0-2</string>
      <string>2-0-3-4</string>
      <string>2-0-3-5</string>
      <string>2-0-4-3</string>
    </ArrayOfString>
    <ArrayOfString>
      <string>0-0-4-3</string>
      <string>0-0-5-0</string>
      <string>0-0-5-1</string>
      <string>0-0-3-0</string>
      <string>0-0-3-1</string>
      <string>0-1-0-2</string>
      <string>0-1-0-2</string>
      <string>2-2-2-1</string>
      <string>2-0-3-4</string>
      <string>2-0-3-5</string>
      <string>0-1-0-2</string>
      <string>0-1-0-2</string>
      <string>2-0-3-4</string>
      <string>2-0-3-5</string>
      <string>2-0-4-3</string>
    </ArrayOfString>
    <ArrayOfString>
      <string>0-0-4-3</string>
      <string>0-0-4-0</string>
      <string>0-0-4-1</string>
      <string>0-0-2-0</string>
      <string>0-0-2-1</string>
      <string>0-1-0-2</string>
      <string>0-1-0-2</string>
      <string>2-2-2-1</string>
      <string>2-0-3-4</string>
      <string>2-0-3-5</string>
      <string>0-1-0-2</string>
      <string>0-1-0-2</string>
      <string>2-0-3-4</string>
      <string>2-0-3-5</string>
      <string>2-0-4-3</string>
    </ArrayOfString>
    <ArrayOfString>
      <string>0-0-4-3</string>
      <string>0-0-5-0</string>
      <string>0-0-5-1</string>
      <string>0-0-3-0</string>
      <string>0-0-3-1</string>
      <string>0-1-0-2</string>
      <string>0-1-0-2</string>
      <string>2-2-2-1</string>
      <string>2-0-3-4</string>
      <string>2-0-3-5</string>
      <string>0-1-0-2</string>
      <string>0-1-0-2</string>
      <string>2-0-3-4</string>
      <string>2-0-3-5</string>
      <string>2-0-4-3</string>
    </ArrayOfString>
    <ArrayOfString>
      <string>0-0-4-3</string>
      <string>0-0-4-0</string>
      <string>0-0-4-1</string>
      <string>0-0-2-0</string>
      <string>0-0-2-1</string>
      <string>0-1-0-2</string>
      <string>0-1-0-2</string>
      <string>2-2-2-1</string>
      <string>2-0-3-4</string>
      <string>2-0-3-5</string>
      <string>0-1-0-2</string>
      <string>0-1-0-2</string>
      <string>2-0-3-4</string>
      <string>2-0-3-5</string>
      <string>2-0-4-3</string>
    </ArrayOfString>
    <ArrayOfString>
      <string>0-0-4-3</string>
      <string>0-0-5-0</string>
      <string>0-0-5-1</string>
      <string>0-0-3-0</string>
      <string>0-0-3-1</string>
      <string>0-1-0-2</string>
      <string>0-1-0-2</string>
      <string>2-2-2-1</string>
      <string>2-0-3-4</string>
      <string>2-0-3-5</string>
      <string>0-1-0-2</string>
      <string>0-1-0-2</string>
      <string>2-0-3-4</string>
      <string>2-0-3-5</string>
      <string>2-0-4-3</string>
    </ArrayOfString>
    <ArrayOfString>
      <string>0-0-4-3</string>
      <string>0-0-4-0</string>
      <string>0-0-4-1</string>
      <string>0-0-2-0</string>
      <string>0-0-2-1</string>
      <string>0-1-0-2</string>
      <string>0-1-0-2</string>
      <string>2-2-2-1</string>
      <string>2-0-3-4</string>
      <string>2-0-3-5</string>
      <string>0-1-0-2</string>
      <string>0-1-0-2</string>
      <string>2-0-3-4</string>
      <string>2-0-3-5</string>
      <string>2-0-4-3</string>
    </ArrayOfString>
    <ArrayOfString>
      <string>0-0-4-3</string>
      <string>0-0-5-0</string>
      <string>0-0-5-1</string>
      <string>0-0-3-0</string>
      <string>0-0-3-1</string>
      <string>0-1-0-2</string>
      <string>0-1-0-2</string>
      <string>2-2-2-1</string>
      <string>2-0-3-4</string>
      <string>2-0-3-5</string>
      <string>0-1-0-2</string>
      <string>0-1-0-2</string>
      <string>2-0-3-4</string>
      <string>2-0-3-5</string>
      <string>2-0-4-3</string>
    </ArrayOfString>
    <ArrayOfString>
      <string>0-0-4-3</string>
      <string>0-0-4-0</string>
      <string>0-0-4-1</string>
      <string>0-0-2-0</string>
      <string>0-0-2-1</string>
      <string>0-1-0-2</string>
      <string>0-1-0-2</string>
      <string>2-2-2-1</string>
      <string>2-0-3-4</string>
      <string>2-0-3-5</string>
      <string>1-1-2-0</string>
      <string>1-1-2-1</string>
      <string>2-0-3-4</string>
      <string>2-0-3-5</string>
      <string>2-0-4-3</string>
    </ArrayOfString>
    <ArrayOfString>
      <string>0-0-4-3</string>
      <string>0-0-5-0</string>
      <string>0-0-5-1</string>
      <string>0-0-3-0</string>
      <string>0-0-3-1</string>
      <string>0-1-0-2</string>
      <string>0-1-0-2</string>
      <string>2-2-2-1</string>
      <string>2-0-3-4</string>
      <string>2-0-3-5</string>
      <string>0-1-0-2</string>
      <string>0-1-0-2</string>
      <string>2-0-3-4</string>
      <string>2-0-3-5</string>
      <string>2-0-4-3</string>
    </ArrayOfString>
    <ArrayOfString>
      <string>0-0-4-3</string>
      <string>0-0-4-0</string>
      <string>0-0-4-1</string>
      <string>0-0-2-0</string>
      <string>0-0-2-1</string>
      <string>0-1-0-2</string>
      <string>0-1-0-2</string>
      <string>0-1-0-2</string>
      <string>0-1-0-2</string>
      <string>0-1-0-2</string>
      <string>0-1-0-2</string>
      <string>0-1-0-2</string>
      <string>0-1-0-2</string>
      <string>3-1-0-7</string>
      <string>3-1-0-7</string>
    </ArrayOfString>
    <ArrayOfString>
      <string>0-0-4-3</string>
      <string>0-0-5-0</string>
      <string>0-0-5-1</string>
      <string>0-0-3-0</string>
      <string>0-0-3-1</string>
      <string>0-1-0-2</string>
      <string>0-1-0-2</string>
      <string>0-1-0-2</string>
      <string>0-1-0-2</string>
      <string>0-1-0-2</string>
      <string>0-1-0-2</string>
      <string>0-1-0-2</string>
      <string>0-1-0-2</string>
      <string>3-1-0-7</string>
      <string>3-1-0-7</string>
    </ArrayOfString>
    <ArrayOfString>
      <string>0-0-4-3</string>
      <string>0-0-4-0</string>
      <string>0-0-4-1</string>
      <string>0-0-2-0</string>
      <string>0-0-2-1</string>
      <string>0-1-0-2</string>
      <string>0-1-0-2</string>
      <string>0-1-0-2</string>
      <string>0-1-0-2</string>
      <string>0-1-0-2</string>
      <string>0-1-0-2</string>
      <string>0-1-0-2</string>
      <string>0-1-0-2</string>
      <string>3-1-0-7</string>
      <string>3-1-0-7</string>
    </ArrayOfString>
    <ArrayOfString>
      <string>0-0-4-3</string>
      <string>0-0-5-0</string>
      <string>0-0-5-1</string>
      <string>0-0-3-0</string>
      <string>0-0-3-1</string>
      <string>0-1-0-2</string>
      <string>0-1-0-2</string>
      <string>0-1-0-2</string>
      <string>0-1-0-2</string>
      <string>0-1-0-2</string>
      <string>0-1-0-2</string>
      <string>0-1-0-2</string>
      <string>0-1-0-2</string>
      <string>3-1-0-7</string>
      <string>3-1-0-7</string>
    </ArrayOfString>
    <ArrayOfString>
      <string>0-0-4-3</string>
      <string>0-0-4-0</string>
      <string>0-0-4-1</string>
      <string>0-0-2-0</string>
      <string>0-0-2-1</string>
      <string>1-1-2-0</string>
      <string>1-1-2-1</string>
      <string>1-1-2-1</string>
      <string>1-1-2-1</string>
      <string>1-1-2-1</string>
      <string>2-0-3-4</string>
      <string>2-0-3-5</string>
      <string>2-0-3-4</string>
      <string>2-0-3-5</string>
      <string>2-0-4-3</string>
    </ArrayOfString>
    <ArrayOfString>
      <string>0-0-4-3</string>
      <string>0-0-5-0</string>
      <string>0-0-5-1</string>
      <string>0-0-3-0</string>
      <string>0-0-3-1</string>
      <string>0-1-0-2</string>
      <string>0-1-0-2</string>
      <string>0-1-0-2</string>
      <string>0-1-0-2</string>
      <string>0-1-0-2</string>
      <string>2-0-3-4</string>
      <string>2-0-3-5</string>
      <string>2-0-3-4</string>
      <string>2-0-3-5</string>
      <string>2-0-4-3</string>
    </ArrayOfString>
    <ArrayOfString>
      <string>0-0-4-3</string>
      <string>0-0-4-0</string>
      <string>0-0-4-1</string>
      <string>0-0-2-0</string>
      <string>0-0-2-1</string>
      <string>0-1-0-2</string>
      <string>0-1-0-2</string>
      <string>0-1-0-2</string>
      <string>0-1-0-2</string>
      <string>0-1-0-2</string>
      <string>2-0-3-4</string>
      <string>2-0-3-5</string>
      <string>2-0-3-4</string>
      <string>2-0-3-5</string>
      <string>2-0-4-3</string>
    </ArrayOfString>
    <ArrayOfString>
      <string>0-0-4-3</string>
      <string>0-0-5-0</string>
      <string>0-0-5-1</string>
      <string>0-0-3-0</string>
      <string>0-0-3-1</string>
      <string>0-1-0-2</string>
      <string>0-1-0-2</string>
      <string>0-1-0-2</string>
      <string>0-1-0-2</string>
      <string>0-1-0-2</string>
      <string>2-0-3-4</string>
      <string>2-0-3-5</string>
      <string>2-0-3-4</string>
      <string>2-0-3-5</string>
      <string>2-0-4-3</string>
    </ArrayOfString>
    <ArrayOfString>
      <string>0-0-4-3</string>
      <string>0-0-4-0</string>
      <string>0-0-4-1</string>
      <string>0-0-2-0</string>
      <string>0-0-2-1</string>
      <string>0-1-0-2</string>
      <string>0-1-0-2</string>
      <string>0-1-0-2</string>
      <string>0-1-0-2</string>
      <string>0-1-0-2</string>
      <string>0-1-0-2</string>
      <string>0-1-0-2</string>
      <string>2-0-3-4</string>
      <string>2-0-3-5</string>
      <string>2-0-4-3</string>
    </ArrayOfString>
    <ArrayOfString>
      <string>0-0-4-3</string>
      <string>0-0-5-0</string>
      <string>0-0-5-1</string>
      <string>0-0-3-0</string>
      <string>0-0-3-1</string>
      <string>0-1-0-2</string>
      <string>0-1-0-2</string>
      <string>0-1-0-2</string>
      <string>0-1-0-2</string>
      <string>1-1-5-0</string>
      <string>0-1-0-2</string>
      <string>0-1-0-2</string>
      <string>2-0-3-4</string>
      <string>2-0-3-5</string>
      <string>2-0-4-3</string>
    </ArrayOfString>
    <ArrayOfString>
      <string>0-0-4-3</string>
      <string>0-0-4-0</string>
      <string>0-0-4-1</string>
      <string>0-0-2-0</string>
      <string>0-0-2-1</string>
      <string>0-1-0-2</string>
      <string>0-1-0-2</string>
      <string>0-1-0-2</string>
      <string>0-1-0-2</string>
      <string>0-1-0-2</string>
      <string>0-1-0-2</string>
      <string>0-1-0-2</string>
      <string>2-0-3-4</string>
      <string>2-0-3-5</string>
      <string>2-0-4-3</string>
    </ArrayOfString>
    <ArrayOfString>
      <string>0-0-4-3</string>
      <string>0-0-5-0</string>
      <string>0-0-5-1</string>
      <string>0-0-3-0</string>
      <string>0-0-3-1</string>
      <string>0-1-0-2</string>
      <string>0-1-0-2</string>
      <string>0-1-0-2</string>
      <string>0-1-0-2</string>
      <string>0-1-0-2</string>
      <string>0-1-0-2</string>
      <string>0-1-0-2</string>
      <string>2-0-3-4</string>
      <string>2-0-3-5</string>
      <string>2-0-4-3</string>
    </ArrayOfString>
    <ArrayOfString>
      <string>0-0-4-3</string>
      <string>0-0-4-0</string>
      <string>0-0-4-1</string>
      <string>0-0-2-0</string>
      <string>0-0-2-1</string>
      <string>0-1-0-2</string>
      <string>0-1-0-2</string>
      <string>0-1-0-2</string>
      <string>0-1-0-2</string>
      <string>1-1-5-0</string>
      <string>0-1-0-2</string>
      <string>0-1-0-2</string>
      <string>2-0-3-4</string>
      <string>2-0-3-5</string>
      <string>2-0-4-3</string>
    </ArrayOfString>
    <ArrayOfString>
      <string>0-0-4-3</string>
      <string>0-0-5-0</string>
      <string>0-0-5-1</string>
      <string>0-0-3-0</string>
      <string>0-0-3-1</string>
      <string>0-1-0-2</string>
      <string>0-1-0-2</string>
      <string>0-1-0-2</string>
      <string>0-1-0-2</string>
      <string>0-1-0-2</string>
      <string>0-1-0-2</string>
      <string>0-1-0-2</string>
      <string>2-0-3-4</string>
      <string>2-0-3-5</string>
      <string>2-0-4-3</string>
    </ArrayOfString>
    <ArrayOfString>
      <string>0-0-4-3</string>
      <string>0-0-4-0</string>
      <string>0-0-4-1</string>
      <string>0-0-2-0</string>
      <string>0-0-2-1</string>
      <string>0-1-0-2</string>
      <string>0-1-0-2</string>
      <string>0-1-0-2</string>
      <string>0-1-0-2</string>
      <string>0-1-0-2</string>
      <string>2-0-3-4</string>
      <string>2-0-3-5</string>
      <string>2-0-3-4</string>
      <string>2-0-3-5</string>
      <string>2-0-4-3</string>
    </ArrayOfString>
    <ArrayOfString>
      <string>0-0-4-3</string>
      <string>0-0-5-0</string>
      <string>0-0-5-1</string>
      <string>0-0-3-0</string>
      <string>0-0-3-1</string>
      <string>0-1-0-2</string>
      <string>0-1-0-2</string>
      <string>0-1-0-2</string>
      <string>0-1-0-2</string>
      <string>0-1-0-2</string>
      <string>2-0-3-4</string>
      <string>2-0-3-5</string>
      <string>2-0-3-4</string>
      <string>2-0-3-5</string>
      <string>2-0-4-3</string>
    </ArrayOfString>
    <ArrayOfString>
      <string>0-0-4-3</string>
      <string>0-0-4-0</string>
      <string>0-0-4-1</string>
      <string>0-0-2-0</string>
      <string>0-0-2-1</string>
      <string>0-1-0-2</string>
      <string>0-1-0-2</string>
      <string>0-1-0-2</string>
      <string>0-1-0-2</string>
      <string>0-1-0-2</string>
      <string>2-0-3-4</string>
      <string>2-0-3-5</string>
      <string>2-0-3-4</string>
      <string>2-0-3-5</string>
      <string>2-0-4-3</string>
    </ArrayOfString>
    <ArrayOfString>
      <string>0-0-4-3</string>
      <string>0-0-5-0</string>
      <string>0-0-5-1</string>
      <string>0-0-3-0</string>
      <string>0-0-3-1</string>
      <string>1-1-2-0</string>
      <string>1-1-2-1</string>
      <string>1-1-2-1</string>
      <string>1-1-2-1</string>
      <string>1-1-2-1</string>
      <string>2-0-3-4</string>
      <string>2-0-3-5</string>
      <string>2-0-3-4</string>
      <string>2-0-3-5</string>
      <string>2-0-4-3</string>
    </ArrayOfString>
    <ArrayOfString>
      <string>0-0-4-3</string>
      <string>0-0-4-0</string>
      <string>0-0-4-1</string>
      <string>0-0-2-0</string>
      <string>0-0-2-1</string>
      <string>0-1-0-2</string>
      <string>0-1-0-2</string>
      <string>0-1-0-2</string>
      <string>0-1-0-2</string>
      <string>0-1-0-2</string>
      <string>0-1-0-2</string>
      <string>0-1-0-2</string>
      <string>0-1-0-2</string>
      <string>3-1-0-7</string>
      <string>3-1-0-7</string>
    </ArrayOfString>
    <ArrayOfString>
      <string>0-0-4-3</string>
      <string>0-0-5-0</string>
      <string>0-0-5-1</string>
      <string>0-0-3-0</string>
      <string>0-0-3-1</string>
      <string>0-1-0-2</string>
      <string>0-1-0-2</string>
      <string>0-1-0-2</string>
      <string>0-1-0-2</string>
      <string>0-1-0-2</string>
      <string>0-1-0-2</string>
      <string>0-1-0-2</string>
      <string>0-1-0-2</string>
      <string>3-1-0-7</string>
      <string>3-1-0-7</string>
    </ArrayOfString>
    <ArrayOfString>
      <string>0-0-4-3</string>
      <string>0-0-4-0</string>
      <string>0-0-4-1</string>
      <string>0-0-2-0</string>
      <string>0-0-2-1</string>
      <string>0-1-0-2</string>
      <string>0-1-0-2</string>
      <string>0-1-0-2</string>
      <string>0-1-0-2</string>
      <string>0-1-0-2</string>
      <string>0-1-0-2</string>
      <string>0-1-0-2</string>
      <string>0-1-0-2</string>
      <string>3-1-0-7</string>
      <string>3-1-0-7</string>
    </ArrayOfString>
    <ArrayOfString>
      <string>0-0-4-3</string>
      <string>0-0-5-0</string>
      <string>0-0-5-1</string>
      <string>0-0-3-0</string>
      <string>0-0-3-1</string>
      <string>0-1-0-2</string>
      <string>0-1-0-2</string>
      <string>0-1-0-2</string>
      <string>0-1-0-2</string>
      <string>0-1-0-2</string>
      <string>0-1-0-2</string>
      <string>0-1-0-2</string>
      <string>0-1-0-2</string>
      <string>3-1-0-7</string>
      <string>3-1-0-7</string>
    </ArrayOfString>
    <ArrayOfString>
      <string>0-0-4-3</string>
      <string>0-0-4-0</string>
      <string>0-0-4-1</string>
      <string>0-0-2-0</string>
      <string>0-0-2-1</string>
      <string>1-1-2-0</string>
      <string>1-1-2-1</string>
      <string>1-1-2-1</string>
      <string>1-1-2-1</string>
      <string>1-1-2-1</string>
      <string>1-1-2-1</string>
      <string>1-1-2-1</string>
      <string>2-0-3-4</string>
      <string>2-0-3-5</string>
      <string>2-0-4-3</string>
    </ArrayOfString>
    <ArrayOfString>
      <string>0-0-4-3</string>
      <string>0-0-5-0</string>
      <string>0-0-5-1</string>
      <string>0-0-3-0</string>
      <string>0-0-3-1</string>
      <string>0-1-0-2</string>
      <string>0-1-0-2</string>
      <string>0-1-0-2</string>
      <string>0-1-0-2</string>
      <string>0-1-0-2</string>
      <string>0-1-0-2</string>
      <string>0-1-0-2</string>
      <string>2-0-3-4</string>
      <string>2-0-3-5</string>
      <string>2-0-4-3</string>
    </ArrayOfString>
    <ArrayOfString>
      <string>0-0-4-3</string>
      <string>0-0-4-0</string>
      <string>0-0-4-1</string>
      <string>0-0-2-0</string>
      <string>0-0-2-1</string>
      <string>0-1-0-2</string>
      <string>0-1-0-2</string>
      <string>0-1-0-2</string>
      <string>0-1-0-2</string>
      <string>1-1-2-5</string>
      <string>1-1-2-6</string>
      <string>1-1-2-6</string>
      <string>2-0-3-4</string>
      <string>2-0-3-5</string>
      <string>2-0-4-3</string>
    </ArrayOfString>
    <ArrayOfString>
      <string>0-0-4-3</string>
      <string>0-0-5-0</string>
      <string>0-0-5-1</string>
      <string>0-0-3-0</string>
      <string>0-0-3-1</string>
      <string>0-1-0-2</string>
      <string>0-1-0-2</string>
      <string>0-1-0-2</string>
      <string>0-1-0-2</string>
      <string>1-1-3-5</string>
      <string>1-1-3-6</string>
      <string>1-1-3-6</string>
      <string>2-0-3-4</string>
      <string>2-0-3-5</string>
      <string>2-0-4-3</string>
    </ArrayOfString>
    <ArrayOfString>
      <string>0-0-4-3</string>
      <string>0-0-0-2</string>
      <string>0-0-2-3</string>
      <string>0-0-1-1</string>
      <string>0-0-2-1</string>
      <string>0-1-0-2</string>
      <string>0-1-0-2</string>
      <string>0-1-0-2</string>
      <string>0-1-0-2</string>
      <string>0-1-0-2</string>
      <string>0-1-0-2</string>
      <string>0-1-0-2</string>
      <string>2-0-3-4</string>
      <string>2-0-3-5</string>
      <string>2-0-4-3</string>
    </ArrayOfString>
    <ArrayOfString>
      <string>0-0-4-3</string>
      <string>0-0-1-2</string>
      <string>0-0-3-3</string>
      <string>0-0-3-2</string>
      <string>0-0-1-3</string>
      <string>1-1-2-0</string>
      <string>1-1-2-1</string>
      <string>1-1-2-1</string>
      <string>1-1-2-1</string>
      <string>1-1-2-1</string>
      <string>1-1-2-1</string>
      <string>1-1-2-1</string>
      <string>2-0-3-4</string>
      <string>2-0-3-5</string>
      <string>2-0-4-3</string>
    </ArrayOfString>
  </Tiles>
  <Enemies>
    <Enemy>
      <Name>Pink Blob</Name>
      <X>112</X>
      <Y>176</Y>
      <MovementType>Horizontal</MovementType>
      <Direction>Right</Direction>
      <SpecialMovement>JumpSmallPause</SpecialMovement>
      <Speed>3</Speed>
      <ShouldFlip>true</ShouldFlip>
      <MinPosition>112</MinPosition>
      <MaxPosition>160</MaxPosition>
      <InitialFlip>false</InitialFlip>
      <ShootingFrequency>0</ShootingFrequency>
      <ShootingInitialFrequency>0</ShootingInitialFrequency>
      <BlinkingType>NotBlinking</BlinkingType>
      <BlinkingFrequency>0</BlinkingFrequency>
      <BlinkingInitialFrequency>0</BlinkingInitialFrequency>
    </Enemy>
    <Enemy>
      <Name>Lava</Name>
      <X>128</X>
      <Y>200</Y>
      <MovementType>None</MovementType>
      <Direction>None</Direction>
      <SpecialMovement>None</SpecialMovement>
      <Speed>0</Speed>
      <ShouldFlip>true</ShouldFlip>
      <MinPosition>0</MinPosition>
      <MaxPosition>0</MaxPosition>
      <InitialFlip>false</InitialFlip>
      <ShootingFrequency>0</ShootingFrequency>
      <ShootingInitialFrequency>0</ShootingInitialFrequency>
      <BlinkingType>NotBlinking</BlinkingType>
      <BlinkingFrequency>0</BlinkingFrequency>
      <BlinkingInitialFrequency>0</BlinkingInitialFrequency>
    </Enemy>
    <Enemy>
      <Name>Green Blob</Name>
      <X>176</X>
      <Y>176</Y>
      <MovementType>Horizontal</MovementType>
      <Direction>Right</Direction>
      <SpecialMovement>JumpSmall</SpecialMovement>
      <Speed>2</Speed>
      <ShouldFlip>true</ShouldFlip>
      <MinPosition>176</MinPosition>
      <MaxPosition>208</MaxPosition>
      <InitialFlip>false</InitialFlip>
      <ShootingFrequency>0</ShootingFrequency>
      <ShootingInitialFrequency>0</ShootingInitialFrequency>
      <BlinkingType>NotBlinking</BlinkingType>
      <BlinkingFrequency>0</BlinkingFrequency>
      <BlinkingInitialFrequency>0</BlinkingInitialFrequency>
    </Enemy>
    <Enemy>
      <Name>Pink Blob</Name>
      <X>256</X>
      <Y>176</Y>
      <MovementType>Horizontal</MovementType>
      <Direction>Right</Direction>
      <SpecialMovement>JumpSmall</SpecialMovement>
      <Speed>1</Speed>
      <ShouldFlip>true</ShouldFlip>
      <MinPosition>256</MinPosition>
      <MaxPosition>368</MaxPosition>
      <InitialFlip>false</InitialFlip>
      <ShootingFrequency>0</ShootingFrequency>
      <ShootingInitialFrequency>0</ShootingInitialFrequency>
      <BlinkingType>NotBlinking</BlinkingType>
      <BlinkingFrequency>0</BlinkingFrequency>
      <BlinkingInitialFrequency>0</BlinkingInitialFrequency>
    </Enemy>
    <Enemy>
      <Name>Green Blob</Name>
      <X>288</X>
      <Y>176</Y>
      <MovementType>Horizontal</MovementType>
      <Direction>Right</Direction>
      <SpecialMovement>JumpBig</SpecialMovement>
      <Speed>1</Speed>
      <ShouldFlip>true</ShouldFlip>
      <MinPosition>288</MinPosition>
      <MaxPosition>336</MaxPosition>
      <InitialFlip>false</InitialFlip>
      <ShootingFrequency>0</ShootingFrequency>
      <ShootingInitialFrequency>0</ShootingInitialFrequency>
      <BlinkingType>NotBlinking</BlinkingType>
      <BlinkingFrequency>0</BlinkingFrequency>
      <BlinkingInitialFrequency>0</BlinkingInitialFrequency>
    </Enemy>
    <Enemy>
      <Name>Lava</Name>
      <X>384</X>
      <Y>200</Y>
      <MovementType>None</MovementType>
      <Direction>None</Direction>
      <SpecialMovement>None</SpecialMovement>
      <Speed>0</Speed>
      <ShouldFlip>true</ShouldFlip>
      <MinPosition>0</MinPosition>
      <MaxPosition>0</MaxPosition>
      <InitialFlip>false</InitialFlip>
      <ShootingFrequency>0</ShootingFrequency>
      <ShootingInitialFrequency>0</ShootingInitialFrequency>
      <BlinkingType>NotBlinking</BlinkingType>
      <BlinkingFrequency>0</BlinkingFrequency>
      <BlinkingInitialFrequency>0</BlinkingInitialFrequency>
    </Enemy>
    <Enemy>
      <Name>Lava</Name>
      <X>416</X>
      <Y>200</Y>
      <MovementType>None</MovementType>
      <Direction>None</Direction>
      <SpecialMovement>None</SpecialMovement>
      <Speed>0</Speed>
      <ShouldFlip>true</ShouldFlip>
      <MinPosition>0</MinPosition>
      <MaxPosition>0</MaxPosition>
      <InitialFlip>false</InitialFlip>
      <ShootingFrequency>0</ShootingFrequency>
      <ShootingInitialFrequency>0</ShootingInitialFrequency>
      <BlinkingType>NotBlinking</BlinkingType>
      <BlinkingFrequency>0</BlinkingFrequency>
      <BlinkingInitialFrequency>0</BlinkingInitialFrequency>
    </Enemy>
    <Enemy>
      <Name>Tank</Name>
      <X>464</X>
      <Y>136</Y>
      <MovementType>None</MovementType>
      <Direction>None</Direction>
      <SpecialMovement>None</SpecialMovement>
      <Speed>0</Speed>
      <ShouldFlip>true</ShouldFlip>
      <MinPosition>0</MinPosition>
      <MaxPosition>0</MaxPosition>
      <InitialFlip>true</InitialFlip>
      <ShootingFrequency>30</ShootingFrequency>
      <ShootingInitialFrequency>30</ShootingInitialFrequency>
      <BlinkingType>NotBlinking</BlinkingType>
      <BlinkingFrequency>0</BlinkingFrequency>
      <BlinkingInitialFrequency>0</BlinkingInitialFrequency>
    </Enemy>
    <Enemy>
      <Name>Tank</Name>
      <X>624</X>
      <Y>136</Y>
      <MovementType>None</MovementType>
      <Direction>None</Direction>
      <SpecialMovement>None</SpecialMovement>
      <Speed>0</Speed>
      <ShouldFlip>true</ShouldFlip>
      <MinPosition>0</MinPosition>
      <MaxPosition>0</MaxPosition>
      <InitialFlip>true</InitialFlip>
      <ShootingFrequency>25</ShootingFrequency>
      <ShootingInitialFrequency>25</ShootingInitialFrequency>
      <BlinkingType>NotBlinking</BlinkingType>
      <BlinkingFrequency>0</BlinkingFrequency>
      <BlinkingInitialFrequency>0</BlinkingInitialFrequency>
    </Enemy>
    <Enemy>
      <Name>Lava</Name>
      <X>672</X>
      <Y>200</Y>
      <MovementType>None</MovementType>
      <Direction>None</Direction>
      <SpecialMovement>None</SpecialMovement>
      <Speed>0</Speed>
      <ShouldFlip>true</ShouldFlip>
      <MinPosition>0</MinPosition>
      <MaxPosition>0</MaxPosition>
      <InitialFlip>false</InitialFlip>
      <ShootingFrequency>0</ShootingFrequency>
      <ShootingInitialFrequency>0</ShootingInitialFrequency>
      <BlinkingType>NotBlinking</BlinkingType>
      <BlinkingFrequency>0</BlinkingFrequency>
      <BlinkingInitialFrequency>0</BlinkingInitialFrequency>
    </Enemy>
    <Enemy>
      <Name>Lava</Name>
      <X>704</X>
      <Y>200</Y>
      <MovementType>None</MovementType>
      <Direction>None</Direction>
      <SpecialMovement>None</SpecialMovement>
      <Speed>0</Speed>
      <ShouldFlip>true</ShouldFlip>
      <MinPosition>0</MinPosition>
      <MaxPosition>0</MaxPosition>
      <InitialFlip>false</InitialFlip>
      <ShootingFrequency>0</ShootingFrequency>
      <ShootingInitialFrequency>0</ShootingInitialFrequency>
      <BlinkingType>NotBlinking</BlinkingType>
      <BlinkingFrequency>0</BlinkingFrequency>
      <BlinkingInitialFrequency>0</BlinkingInitialFrequency>
    </Enemy>
  </Enemies>
  <Elevators>
    <Elevator>
      <X>384</X>
      <Y>192</Y>
      <Size>4</Size>
      <MovementType>Horizontal</MovementType>
      <Speed>0.5</Speed>
      <MinPosition>384</MinPosition>
      <MaxPosition>416</MaxPosition>
      <Direction>Right</Direction>
    </Elevator>
  </Elevators>
  <PlayerStartingPosition>
    <X>36</X>
    <Y>191</Y>
  </PlayerStartingPosition>
  <ScrollSpeed>1</ScrollSpeed>
  <ExitPosition>
    <X>772</X>
    <Y>157</Y>
  </ExitPosition>
  <Song>song_index_song_stage_base</Song>
  <StopSong>true</StopSong>
</Level>